neuro_san_web_client/__init__.py
neuro_san_web_client/agent_log_processor.py
neuro_san_web_client/agents_diagram_builder.py
neuro_san_web_client/app.py
neuro_san_web_client/static/css/NeuroAI.jpg
neuro_san_web_client/static/css/styles.css
neuro_san_web_client/static/js/scripts.js
neuro_san_web_client/templates/index.html
neuro_san_web_client-0.1.13.dist-info/licenses/LICENSE.txt
neuro_san_web_client-0.1.13.dist-info/METADATA
neuro_san_web_client-0.1.13.dist-info/WHEEL
neuro_san_web_client-0.1.13.dist-info/top_level.txt
neuro_san_web_client-0.1.13.dist-info/RECORD
