Metadata-Version: 2.4
Name: neuro-san-web-client
Version: 0.1.13
Summary: Web client demo interface for neuro-san
Author-email: Olivier Francon <olivier.francon@cognizant.com>
License-Expression: LicenseRef-CognizantAcademicSource
Project-URL: Homepage, https://github.com/cognizant-ai-lab/neuro-san-web-client
Project-URL: Repository, https://github.com/cognizant-ai-lab/neuro-san-web-client
Project-URL: Documentation, https://github.com/cognizant-ai-lab/neuro-san-web-client#readme
Keywords: LLM,langchain,agent,multi-agent
Classifier: Programming Language :: Python :: 3
Classifier: Operating System :: OS Independent
Classifier: Development Status :: 3 - Alpha
Classifier: Intended Audience :: Developers
Requires-Python: >=3.10
License-File: LICENSE.txt
Requires-Dist: neuro_san>=0.6.13
Requires-Dist: Flask==3.1.2
Requires-Dist: Flask-SocketIO==5.5.1
Requires-Dist: pyOpenSSL==25.3.0
Requires-Dist: PyJWT>=2.10.1
Requires-Dist: hvac==2.4.0
Requires-Dist: eventlet==0.40.4
Requires-Dist: pyvis~=0.3.2
Dynamic: license-file
